Workbook

Sheet Entradas
A1: CONTROLE DE ESTOQUE — ENTRADAS
A2: Registre aqui todas as compras feitas no atacado
A5: Data | B5: Fornecedor | C5: Produto | D5: Categoria | E5: Qtd | F5: Custo Unit. (R$) | G5: Frete Rateado (R$) | H5: Custo Total (R$)
A6: 15/03/2025 | B6: K2B Modas | C6: Calça jeans skinny | D6: Jeans Feminino | E6: 10 | F6: 45 | G6: 4 | H6: =E6*(F6+G6) -> 490
A7: 15/03/2025 | B7: Sawary | C7: Blusa estampada | D7: Polo do Brás | E7: 20 | F7: 22 | G7: 4 | H7: =E7*(F7+G7) -> 520
A8: 22/03/2025 | B8: Pit Bull | C8: Calça flare | D8: Jeans Feminino | E8: 5 | F8: 80 | G8: 6 | H8: =E8*(F8+G8) -> 430
H9: =IFERROR(E9*(F9+G9),"") -> 0
H10: =IFERROR(E10*(F10+G10),"") -> 0
H11: =IFERROR(E11*(F11+G11),"") -> 0
H12: =IFERROR(E12*(F12+G12),"") -> 0
H13: =IFERROR(E13*(F13+G13),"") -> 0
H14: =IFERROR(E14*(F14+G14),"") -> 0
H15: =IFERROR(E15*(F15+G15),"") -> 0
H16: =IFERROR(E16*(F16+G16),"") -> 0
H17: =IFERROR(E17*(F17+G17),"") -> 0
H18: =IFERROR(E18*(F18+G18),"") -> 0
H19: =IFERROR(E19*(F19+G19),"") -> 0
H20: =IFERROR(E20*(F20+G20),"") -> 0
... H49: =IFERROR(E49*(F49+G49),"") -> 0
A51: TOTAL INVESTIDO | H51: =SUM(H6:H50) -> 1440

Sheet Saidas
A1: CONTROLE DE ESTOQUE — SAIDAS (VENDAS)
A2: Registre aqui todas as vendas realizadas
A5: Data | B5: Cliente | C5: Produto | D5: Qtd | E5: Valor Unit. (R$) | F5: Pagamento | G5: Total (R$)
A6: 20/03/2025 | B6: Maria Silva | C6: Calça jeans skinny | D6: 1 | E6: 129.9 | F6: Pix | G6: =D6*E6 -> 129.9
A7: 21/03/2025 | B7: Ana Souza | C7: Blusa estampada | D7: 2 | E7: 65 | F7: Cartão | G7: =D7*E7 -> 130
A8: 23/03/2025 | B8: Joana B. | C8: Calça flare | D8: 1 | E8: 199 | F8: Pix | G8: =D8*E8 -> 199
G9: =IFERROR(D9*E9,"") -> 0
G10: =IFERROR(D10*E10,"") -> 0
G11: =IFERROR(D11*E11,"") -> 0
G12: =IFERROR(D12*E12,"") -> 0
G13: =IFERROR(D13*E13,"") -> 0
G14: =IFERROR(D14*E14,"") -> 0
G15: =IFERROR(D15*E15,"") -> 0
G16: =IFERROR(D16*E16,"") -> 0
G17: =IFERROR(D17*E17,"") -> 0
G18: =IFERROR(D18*E18,"") -> 0
G19: =IFERROR(D19*E19,"") -> 0
G20: =IFERROR(D20*E20,"") -> 0
... G49: =IFERROR(D49*E49,"") -> 0
A51: FATURAMENTO TOTAL | G51: =SUM(G6:G50) -> 458.9

Sheet Resumo
A1: RESUMO FINANCEIRO
A2: Dashboard automatico — atualiza com base nas abas Entradas e Saidas
A5: 💰 Total Investido | C5: =Entradas!H51 -> 1440 | D5: Quanto voce gastou
A7: 📈 Total Faturado | C7: =Saidas!G51 -> 458.9 | D7: Quanto voce recebeu
A9: 💎 Lucro Bruto | C9: =Saidas!G51-Entradas!H51 -> -981.1 | D9: Diferenca entre os dois
A11: 📊 Margem de Lucro | C11: =IFERROR((Saidas!G51-Entradas!H51)/Saidas!G51,0) -> -2.1379385 | D11: Percentual de lucro
A13: 🚀 ROI | C13: =IFERROR((Saidas!G51-Entradas!H51)/Entradas!H51,0) -> -0.68131944 | D13: Retorno sobre investimento
A16: 💡 COMO USAR
A17: • Aba ENTRADAS: registre cada compra que faz no atacado (uma linha por produto).
A18: • Aba SAIDAS: registre cada venda que realiza (uma linha por venda).
A19: • Aba RESUMO: este painel atualiza automaticamente com seus numeros.
A20: • Margem de Lucro saudavel: 50% ou mais. ROI saudavel: 80% ou mais.
A21: • Se Lucro Bruto ficar negativo, voce esta vendendo mais barato que o custo!
